CHANGELOG.rst
LICENSE.txt
MANIFEST.in
README.rst
setup.py
docs/howitworks.rst
docs/index.rst
docs/options.rst
docs/tutorial.rst
slumber/__init__.py
slumber/auth.py
slumber/exceptions.py
slumber/serialize.py
slumber/utils.py
slumber_fork.egg-info/PKG-INFO
slumber_fork.egg-info/SOURCES.txt
slumber_fork.egg-info/dependency_links.txt
slumber_fork.egg-info/not-zip-safe
slumber_fork.egg-info/requires.txt
slumber_fork.egg-info/top_level.txt