Metadata-Version: 1.0
Name: slumber-fork
Version: 0.6.3
Summary: Fork of Slumber, A library that makes consuming a REST API easier and more convenient
Home-page: http://github.com/futurice/slumber
Author: Samuel Giles
Author-email: sam.e.giles@gmail.com
License: UNKNOWN
Platform: UNKNOWN
